{"rowsData":[{"id":7501,"name":"Ley Druid","cost":"2$G","type":"Creature","subType":"Human Druid","power":"1","toughness":"1","abilities":"{tap}: Untap target land.","implemented":true,"requested":false,"tested":false,"bugged":false,"developer":null,"editions":[{"rarity":"Uncommon","gathererId":"161","mtgoImageId":"00141","expansionCode":"1E","expansionName":"Limited Edition Alpha","cardNumber":"114"},{"rarity":"Uncommon","gathererId":"456","mtgoImageId":"00141","expansionCode":"2E","expansionName":"Limited Edition Beta","cardNumber":"114"},{"rarity":"Uncommon","gathererId":"758","mtgoImageId":"00141","expansionCode":"2U","expansionName":"Unlimited Edition","cardNumber":"114"},{"rarity":"Uncommon","gathererId":"1255","mtgoImageId":"00141","expansionCode":"3E","expansionName":"Revised Edition","cardNumber":"113"},{"rarity":"Uncommon","gathererId":"2223","mtgoImageId":"00141","expansionCode":"4E","expansionName":"Fourth Edition","cardNumber":"140"},{"rarity":"Common","gathererId":"3991","mtgoImageId":"00141","expansionCode":"5E","expansionName":"Fifth Edition","cardNumber":"170"},{"rarity":"Uncommon","gathererId":"83099","mtgoImageId":"86907","expansionCode":"9ED","expansionName":"Ninth Edition","cardNumber":"251"}],"otherSide":null},{"id":7502,"name":"Llanowar Behemoth","cost":"3$G$G","type":"Creature","subType":"Elemental","power":"4","toughness":"4","abilities":"Tap an untapped creature you control: Llanowar Behemoth gets +1/+1 until end of turn.","implemented":true,"requested":false,"tested":false,"bugged":false,"developer":null,"editions":[{"rarity":"Uncommon","gathererId":"4520","mtgoImageId":"02870","expansionCode":"WL","expansionName":"Weatherlight","cardNumber":"74"},{"rarity":"Uncommon","gathererId":"45429","mtgoImageId":"02870","expansionCode":"8ED","expansionName":"Eighth Edition","cardNumber":"261"},{"rarity":"Uncommon","gathererId":"83152","mtgoImageId":"86912","expansionCode":"9ED","expansionName":"Ninth Edition","cardNumber":"252"}],"otherSide":null},{"id":7503,"name":"Maro","cost":"2$G$G","type":"Creature","subType":"Elemental","power":"*","toughness":"*","abilities":"Maro's power and toughness are each equal to the number of cards in your hand.","implemented":true,"requested":false,"tested":false,"bugged":false,"developer":null,"editions":[{"rarity":"Rare","gathererId":"3397","mtgoImageId":"01961","expansionCode":"MI","expansionName":"Mirage","cardNumber":"126"},{"rarity":"Rare","gathererId":"14718","mtgoImageId":"01961","expansionCode":"6E","expansionName":"Sixth Edition","cardNumber":"241"},{"rarity":"Rare","gathererId":"12965","mtgoImageId":"27700","expansionCode":"7E","expansionName":"Seventh Edition","cardNumber":"256"},{"rarity":"Rare","gathererId":"45445","mtgoImageId":"01961","expansionCode":"8ED","expansionName":"Eighth Edition","cardNumber":"264"},{"rarity":"Rare","gathererId":"83161","mtgoImageId":"01961","expansionCode":"9ED","expansionName":"Ninth Edition","cardNumber":"254"}],"otherSide":null},{"id":7504,"name":"Natural Affinity","cost":"2$G","type":"Instant","subType":null,"power":null,"toughness":null,"abilities":"All lands become 2/2 creatures until end of turn. They're still lands.","implemented":true,"requested":false,"tested":false,"bugged":false,"developer":null,"editions":[{"rarity":"Rare","gathererId":"19875","mtgoImageId":"19297","expansionCode":"MM","expansionName":"Mercadian Masques","cardNumber":"260"},{"rarity":"Rare","gathererId":"45449","mtgoImageId":"19297","expansionCode":"8ED","expansionName":"Eighth Edition","cardNumber":"269"},{"rarity":"Rare","gathererId":"83182","mtgoImageId":"19297","expansionCode":"9ED","expansionName":"Ninth Edition","cardNumber":"256"}],"otherSide":null},{"id":7505,"name":"Norwood Ranger","cost":"G","type":"Creature","subType":"Elf Scout","power":"1","toughness":"2","abilities":"","implemented":true,"requested":false,"tested":false,"bugged":false,"developer":null,"editions":[{"rarity":"Common","gathererId":"6636","mtgoImageId":"04785","expansionCode":"P2","expansionName":"Portal Second Age","cardNumber":"78"},{"rarity":"Common","gathererId":"21052","mtgoImageId":null,"expansionCode":"P3","expansionName":"Starter 1999","cardNumber":"138"},{"rarity":"Common","gathererId":"45409","mtgoImageId":"04785","expansionCode":"8ED","expansionName":"Eighth Edition","cardNumber":"271"},{"rarity":"Common","gathererId":"83188","mtgoImageId":"04785","expansionCode":"9ED","expansionName":"Ninth Edition","cardNumber":"260"}],"otherSide":null},{"id":7506,"name":"River Bear","cost":"3$G","type":"Creature","subType":"Bear","power":"3","toughness":"3","abilities":"Islandwalk <i>(This creature can't be blocked as long as defending player controls an Island.)</i>","implemented":true,"requested":false,"tested":false,"bugged":false,"developer":null,"editions":[{"rarity":"Uncommon","gathererId":"6626","mtgoImageId":"04775","expansionCode":"P2","expansionName":"Portal Second Age","cardNumber":"84"},{"rarity":"Uncommon","gathererId":"83022","mtgoImageId":"04775","expansionCode":"9ED","expansionName":"Ninth Edition","cardNumber":"266"}],"otherSide":null},{"id":7507,"name":"Scaled Wurm","cost":"7$G","type":"Creature","subType":"Wurm","power":"7","toughness":"6","abilities":"","implemented":true,"requested":false,"tested":false,"bugged":false,"developer":null,"editions":[{"rarity":"Common","gathererId":"2586","mtgoImageId":"01347","expansionCode":"IA","expansionName":"Ice Age","cardNumber":"150"},{"rarity":"Common","gathererId":"4005","mtgoImageId":"01347","expansionCode":"5E","expansionName":"Fifth Edition","cardNumber":"184"},{"rarity":"Common","gathererId":"16452","mtgoImageId":"01347","expansionCode":"6E","expansionName":"Sixth Edition","cardNumber":"251"},{"rarity":"Common","gathererId":"83272","mtgoImageId":"86923","expansionCode":"9ED","expansionName":"Ninth Edition","cardNumber":"269"},{"rarity":"Common","gathererId":"382352","mtgoImageId":null,"expansionCode":"CNS","expansionName":"Magic: The Gathering-Conspiracy","cardNumber":"178"}],"otherSide":null},{"id":7508,"name":"Silklash Spider","cost":"3$G$G","type":"Creature","subType":"Spider","power":"2","toughness":"7","abilities":"Reach <i>(This creature can block creatures with flying.)</i>${X}{G}{G}: Silklash Spider deals X damage to each creature with flying.","implemented":true,"requested":false,"tested":false,"bugged":false,"developer":null,"editions":[{"rarity":"Rare","gathererId":"39687","mtgoImageId":"43204","expansionCode":"ONS","expansionName":"Onslaught","cardNumber":"281"},{"rarity":"Rare","gathererId":"83463","mtgoImageId":"43204","expansionCode":"9ED","expansionName":"Ninth Edition","cardNumber":"271"},{"rarity":"Rare","gathererId":"292718","mtgoImageId":"43204","expansionCode":"M13","expansionName":"Magic 2013","cardNumber":"191"},{"rarity":"Rare","gathererId":"376499","mtgoImageId":"43204","expansionCode":"C13","expansionName":"Commander 2013 Edition","cardNumber":"169"},{"rarity":"Rare","gathererId":"389672","mtgoImageId":"43204","expansionCode":"C14","expansionName":"Commander 2014 Edition","cardNumber":"214"}],"otherSide":null},{"id":7509,"name":"Stream of Life","cost":"X$G","type":"Sorcery","subType":null,"power":null,"toughness":null,"abilities":"Target player gains X life.","implemented":true,"requested":false,"tested":false,"bugged":false,"developer":null,"editions":[{"rarity":"Common","gathererId":"173","mtgoImageId":"00241","expansionCode":"1E","expansionName":"Limited Edition Alpha","cardNumber":"126"},{"rarity":"Common","gathererId":"468","mtgoImageId":"00241","expansionCode":"2E","expansionName":"Limited Edition Beta","cardNumber":"126"},{"rarity":"Common","gathererId":"770","mtgoImageId":"00241","expansionCode":"2U","expansionName":"Unlimited Edition","cardNumber":"126"},{"rarity":"Common","gathererId":"1266","mtgoImageId":"00241","expansionCode":"3E","expansionName":"Revised Edition","cardNumber":"124"},{"rarity":"Common","gathererId":"2239","mtgoImageId":"00241","expansionCode":"4E","expansionName":"Fourth Edition","cardNumber":"156"},{"rarity":"Common","gathererId":"4011","mtgoImageId":"02487","expansionCode":"5E","expansionName":"Fifth Edition","cardNumber":"190"},{"rarity":"Common","gathererId":"14687","mtgoImageId":"02487","expansionCode":"6E","expansionName":"Sixth Edition","cardNumber":"254"},{"rarity":"Common","gathererId":"11517","mtgoImageId":"27814","expansionCode":"7E","expansionName":"Seventh Edition","cardNumber":"272"},{"rarity":"Uncommon","gathererId":"45419","mtgoImageId":"27814","expansionCode":"8ED","expansionName":"Eighth Edition","cardNumber":"282"},{"rarity":"Uncommon","gathererId":"83284","mtgoImageId":"27814","expansionCode":"9ED","expansionName":"Ninth Edition","cardNumber":"272"}],"otherSide":null},{"id":7510,"name":"Summer Bloom","cost":"1$G","type":"Sorcery","subType":null,"power":null,"toughness":null,"abilities":"You may play up to three additional lands this turn.","implemented":true,"requested":false,"tested":false,"bugged":false,"developer":null,"editions":[{"rarity":"Uncommon","gathererId":"3679","mtgoImageId":"02263","expansionCode":"VI","expansionName":"Visions","cardNumber":"72"},{"rarity":"Rare","gathererId":"4319","mtgoImageId":"06675","expansionCode":"PO","expansionName":"Portal","cardNumber":"113"},{"rarity":"Uncommon","gathererId":"14696","mtgoImageId":"06675","expansionCode":"6E","expansionName":"Sixth Edition","cardNumber":"255"},{"rarity":"Rare","gathererId":"21078","mtgoImageId":null,"expansionCode":"P3","expansionName":"Starter 1999","cardNumber":"144"},{"rarity":"Uncommon","gathererId":"84694","mtgoImageId":"02263","expansionCode":"9ED","expansionName":"Ninth Edition","cardNumber":"273"}],"otherSide":null},{"id":7511,"name":"Tree Monkey","cost":"G","type":"Creature","subType":"Ape","power":"1","toughness":"1","abilities":"Reach <i>(This creature can block creatures with flying.)</i>","implemented":true,"requested":false,"tested":false,"bugged":false,"developer":null,"editions":[{"rarity":"Common","gathererId":"6619","mtgoImageId":"04768","expansionCode":"P2","expansionName":"Portal Second Age","cardNumber":"88"},{"rarity":"Common","gathererId":"84665","mtgoImageId":"86958","expansionCode":"9ED","expansionName":"Ninth Edition","cardNumber":"275"}],"otherSide":null},{"id":7512,"name":"Verduran Enchantress","cost":"1$G$G","type":"Creature","subType":"Human Druid","power":"0","toughness":"2","abilities":"Whenever you cast an enchantment spell, you may draw a card.","implemented":true,"requested":false,"tested":false,"bugged":false,"developer":null,"editions":[{"rarity":"Rare","gathererId":"178","mtgoImageId":"00267","expansionCode":"1E","expansionName":"Limited Edition Alpha","cardNumber":"131"},{"rarity":"Rare","gathererId":"473","mtgoImageId":"00267","expansionCode":"2E","expansionName":"Limited Edition Beta","cardNumber":"131"},{"rarity":"Rare","gathererId":"775","mtgoImageId":"00267","expansionCode":"2U","expansionName":"Unlimited Edition","cardNumber":"131"},{"rarity":"Rare","gathererId":"1272","mtgoImageId":"00267","expansionCode":"3E","expansionName":"Revised Edition","cardNumber":"130"},{"rarity":"Rare","gathererId":"2248","mtgoImageId":"00267","expansionCode":"4E","expansionName":"Fourth Edition","cardNumber":"165"},{"rarity":"Rare","gathererId":"4020","mtgoImageId":"00267","expansionCode":"5E","expansionName":"Fifth Edition","cardNumber":"199"},{"rarity":"Rare","gathererId":"11558","mtgoImageId":"00267","expansionCode":"6E","expansionName":"Sixth Edition","cardNumber":"264"},{"rarity":"Rare","gathererId":"25594","mtgoImageId":"27851","expansionCode":"7E","expansionName":"Seventh Edition","cardNumber":"280"},{"rarity":"Rare","gathererId":"45443","mtgoImageId":"27851","expansionCode":"8ED","expansionName":"Eighth Edition","cardNumber":"285"},{"rarity":"Rare","gathererId":"83320","mtgoImageId":"27851","expansionCode":"9ED","expansionName":"Ninth Edition","cardNumber":"279"}],"otherSide":null},{"id":7513,"name":"Master Healer","cost":"4$W","type":"Creature","subType":"Human Cleric","power":"1","toughness":"4","abilities":"{tap}: Prevent the next 4 damage that would be dealt to target creature or player this turn.","implemented":true,"requested":false,"tested":false,"bugged":false,"developer":null,"editions":[{"rarity":"Rare","gathererId":"15874","mtgoImageId":"15710","expansionCode":"CG","expansionName":"Urza's Destiny","cardNumber":"12"},{"rarity":"Rare","gathererId":"15790","mtgoImageId":"27701","expansionCode":"7E","expansionName":"Seventh Edition","cardNumber":"27"},{"rarity":"Rare","gathererId":"45213","mtgoImageId":"27701","expansionCode":"8ED","expansionName":"Eighth Edition","cardNumber":"30"},{"rarity":"Rare","gathererId":"83163","mtgoImageId":"15710","expansionCode":"9ED","expansionName":"Ninth Edition","cardNumber":"28"}],"otherSide":null},{"id":7514,"name":"Web","cost":"G","type":"Enchantment","subType":"Aura","power":null,"toughness":null,"abilities":"Enchant creature <i>(Target a creature as you cast this. This card enters the battlefield attached to that creature.)</i>$Enchanted creature gets +0/+2 and has reach. <i>(It can block creatures with flying.)</i>","implemented":true,"requested":false,"tested":false,"bugged":false,"developer":null,"editions":[{"rarity":"Rare","gathererId":"184","mtgoImageId":"00285","expansionCode":"1E","expansionName":"Limited Edition Alpha","cardNumber":"137"},{"rarity":"Rare","gathererId":"479","mtgoImageId":"00285","expansionCode":"2E","expansionName":"Limited Edition Beta","cardNumber":"137"},{"rarity":"Rare","gathererId":"781","mtgoImageId":"00285","expansionCode":"2U","expansionName":"Unlimited Edition","cardNumber":"137"},{"rarity":"Rare","gathererId":"1278","mtgoImageId":"00285","expansionCode":"3E","expansionName":"Revised Edition","cardNumber":"136"},{"rarity":"Rare","gathererId":"2254","mtgoImageId":"00285","expansionCode":"4E","expansionName":"Fourth Edition","cardNumber":"171"},{"rarity":"Uncommon","gathererId":"83994","mtgoImageId":"86942","expansionCode":"9ED","expansionName":"Ninth Edition","cardNumber":"281"}],"otherSide":null},{"id":7515,"name":"Weird Harvest","cost":"X$G$G","type":"Sorcery","subType":null,"power":null,"toughness":null,"abilities":"Each player may search his or her library for up to X creature cards, reveal those cards, and put them into his or her hand. Then each player who searched his or her library this way shuffles it.","implemented":true,"requested":false,"tested":false,"bugged":false,"developer":null,"editions":[{"rarity":"Rare","gathererId":"39680","mtgoImageId":"43199","expansionCode":"ONS","expansionName":"Onslaught","cardNumber":"299"},{"rarity":"Rare","gathererId":"83974","mtgoImageId":"43199","expansionCode":"9ED","expansionName":"Ninth Edition","cardNumber":"282"}],"otherSide":null},{"id":7516,"name":"Wood Elves","cost":"2$G","type":"Creature","subType":"Elf Scout","power":"1","toughness":"1","abilities":"When Wood Elves enters the battlefield, search your library for a Forest card and put that card onto the battlefield. Then shuffle your library.","implemented":true,"requested":false,"tested":false,"bugged":false,"developer":null,"editions":[{"rarity":"Rare","gathererId":"4327","mtgoImageId":"06682","expansionCode":"PO","expansionName":"Portal","cardNumber":"121"},{"rarity":"Common","gathererId":"6135","mtgoImageId":"05439","expansionCode":"EX","expansionName":"Exodus","cardNumber":"130"},{"rarity":"Uncommon","gathererId":"20224","mtgoImageId":null,"expansionCode":"P3","expansionName":"Starter 1999","cardNumber":"153"},{"rarity":"Common","gathererId":"13147","mtgoImageId":"27867","expansionCode":"7E","expansionName":"Seventh Edition","cardNumber":"284"},{"rarity":"Common","gathererId":"45400","mtgoImageId":"27867","expansionCode":"8ED","expansionName":"Eighth Edition","cardNumber":"289"},{"rarity":"Common","gathererId":"83336","mtgoImageId":"27867","expansionCode":"9ED","expansionName":"Ninth Edition","cardNumber":"283"},{"rarity":"Common","gathererId":"159038","mtgoImageId":"27867","expansionCode":"EVG","expansionName":"Duel Decks: Elves vs. Goblins","cardNumber":"18"},{"rarity":"Common","gathererId":"389752","mtgoImageId":"27867","expansionCode":"C14","expansionName":"Commander 2014 Edition","cardNumber":"226"},{"rarity":"Common","gathererId":"405454","mtgoImageId":null,"expansionCode":"C15","expansionName":"Commander 2015","cardNumber":"212"},{"rarity":"Common","gathererId":"417448","mtgoImageId":null,"expansionCode":"DDR","expansionName":"Duel Decks: Nissa vs. Ob Nixilis","cardNumber":"25"}],"otherSide":null},{"id":7517,"name":"Zodiac Monkey","cost":"1$G","type":"Creature","subType":"Ape","power":"2","toughness":"1","abilities":"Forestwalk <i>(This creature can't be blocked as long as defending player controls a Forest.)</i>","implemented":true,"requested":false,"tested":false,"bugged":false,"developer":null,"editions":[{"rarity":"Common","gathererId":"10558","mtgoImageId":"09111","expansionCode":"PK","expansionName":"Portal Three Kingdoms","cardNumber":"160"},{"rarity":"Common","gathererId":"83237","mtgoImageId":"86921","expansionCode":"9ED","expansionName":"Ninth Edition","cardNumber":"285"}],"otherSide":null},{"id":7518,"name":"Aladdin's Ring","cost":"8","type":"Artifact","subType":null,"power":null,"toughness":null,"abilities":"{8}, {tap}: Aladdin's Ring deals 4 damage to target creature or player.","implemented":true,"requested":false,"tested":false,"bugged":false,"developer":null,"editions":[{"rarity":"Rare","gathererId":"901","mtgoImageId":"00306","expansionCode":"AN","expansionName":"Arabian Nights","cardNumber":"71"},{"rarity":"Rare","gathererId":"1093","mtgoImageId":"00306","expansionCode":"3E","expansionName":"Revised Edition","cardNumber":"232"},{"rarity":"Rare","gathererId":"2015","mtgoImageId":"00306","expansionCode":"4E","expansionName":"Fourth Edition","cardNumber":"310"},{"rarity":"Rare","gathererId":"3758","mtgoImageId":"02301","expansionCode":"5E","expansionName":"Fifth Edition","cardNumber":"346"},{"rarity":"Rare","gathererId":"14770","mtgoImageId":"02301","expansionCode":"6E","expansionName":"Sixth Edition","cardNumber":"271"},{"rarity":"Rare","gathererId":"11145","mtgoImageId":"27530","expansionCode":"7E","expansionName":"Seventh Edition","cardNumber":"286"},{"rarity":"Rare","gathererId":"45487","mtgoImageId":"27530","expansionCode":"8ED","expansionName":"Eighth Edition","cardNumber":"291"},{"rarity":"Rare","gathererId":"82989","mtgoImageId":"27530","expansionCode":"9ED","expansionName":"Ninth Edition","cardNumber":"286"}],"otherSide":null},{"id":7519,"name":"Beast of Burden","cost":"6","type":"Artifact Creature","subType":"Golem","power":"*","toughness":"*","abilities":"Beast of Burden's power and toughness are each equal to the number of creatures on the battlefield.","implemented":true,"requested":false,"tested":false,"bugged":false,"developer":null,"editions":[{"rarity":"Rare","gathererId":"12504","mtgoImageId":"09503","expansionCode":"GU","expansionName":"Urza's Legacy","cardNumber":"122"},{"rarity":"Rare","gathererId":"15861","mtgoImageId":"27541","expansionCode":"7E","expansionName":"Seventh Edition","cardNumber":"287"},{"rarity":"Rare","gathererId":"45488","mtgoImageId":"27541","expansionCode":"8ED","expansionName":"Eighth Edition","cardNumber":"292"},{"rarity":"Rare","gathererId":"83002","mtgoImageId":"27541","expansionCode":"9ED","expansionName":"Ninth Edition","cardNumber":"288"}],"otherSide":null},{"id":7520,"name":"Dancing Scimitar","cost":"4","type":"Artifact Creature","subType":"Spirit","power":"1","toughness":"5","abilities":"Flying <i>(This creature can't be blocked except by creatures with flying or reach.)</i>","implemented":true,"requested":false,"tested":false,"bugged":false,"developer":null,"editions":[{"rarity":"Rare","gathererId":"905","mtgoImageId":"00319","expansionCode":"AN","expansionName":"Arabian Nights","cardNumber":"75"},{"rarity":"Rare","gathererId":"1104","mtgoImageId":"00319","expansionCode":"3E","expansionName":"Revised Edition","cardNumber":"243"},{"rarity":"Rare","gathererId":"2036","mtgoImageId":"00319","expansionCode":"4E","expansionName":"Fourth Edition","cardNumber":"331"},{"rarity":"Rare","gathererId":"3774","mtgoImageId":"00319","expansionCode":"5E","expansionName":"Fifth Edition","cardNumber":"362"},{"rarity":"Rare","gathererId":"14773","mtgoImageId":"00319","expansionCode":"6E","expansionName":"Sixth Edition","cardNumber":"279"},{"rarity":"Uncommon","gathererId":"84114","mtgoImageId":"86725","expansionCode":"9ED","expansionName":"Ninth Edition","cardNumber":"292"}],"otherSide":null},{"id":7521,"name":"Defense Grid","cost":"2","type":"Artifact","subType":null,"power":null,"toughness":null,"abilities":"Each spell costs {3} more to cast except during its controller's turn.","implemented":true,"requested":false,"tested":false,"bugged":false,"developer":null,"editions":[{"rarity":"Rare","gathererId":"8897","mtgoImageId":"14066","expansionCode":"GU","expansionName":"Urza's Legacy","cardNumber":"125"},{"rarity":"Rare","gathererId":"45481","mtgoImageId":"14066","expansionCode":"8ED","expansionName":"Eighth Edition","cardNumber":"296"},{"rarity":"Rare","gathererId":"83051","mtgoImageId":"14066","expansionCode":"9ED","expansionName":"Ninth Edition","cardNumber":"293"}],"otherSide":null},{"id":7522,"name":"Disrupting Scepter","cost":"3","type":"Artifact","subType":null,"power":null,"toughness":null,"abilities":"{3}, {tap}: Target player discards a card. Activate this ability only during your turn.","implemented":true,"requested":false,"tested":false,"bugged":false,"developer":null,"editions":[{"rarity":"Rare","gathererId":"13","mtgoImageId":"00066","expansionCode":"1E","expansionName":"Limited Edition Alpha","cardNumber":"242"},{"rarity":"Rare","gathererId":"308","mtgoImageId":"00066","expansionCode":"2E","expansionName":"Limited Edition Beta","cardNumber":"244"},{"rarity":"Rare","gathererId":"610","mtgoImageId":"00066","expansionCode":"2U","expansionName":"Unlimited Edition","cardNumber":"243"},{"rarity":"Rare","gathererId":"1106","mtgoImageId":"00066","expansionCode":"3E","expansionName":"Revised Edition","cardNumber":"245"},{"rarity":"Rare","gathererId":"2039","mtgoImageId":"00066","expansionCode":"4E","expansionName":"Fourth Edition","cardNumber":"334"},{"rarity":"Rare","gathererId":"3777","mtgoImageId":"02351","expansionCode":"5E","expansionName":"Fifth Edition","cardNumber":"365"},{"rarity":"Rare","gathererId":"11240","mtgoImageId":"02351","expansionCode":"6E","expansionName":"Sixth Edition","cardNumber":"281"},{"rarity":"Rare","gathererId":"15868","mtgoImageId":"27593","expansionCode":"7E","expansionName":"Seventh Edition","cardNumber":"293"},{"rarity":"Rare","gathererId":"45476","mtgoImageId":"02351","expansionCode":"8ED","expansionName":"Eighth Edition","cardNumber":"298"},{"rarity":"Rare","gathererId":"83058","mtgoImageId":"02351","expansionCode":"9ED","expansionName":"Ninth Edition","cardNumber":"295"}],"otherSide":null},{"id":7523,"name":"Fellwar Stone","cost":"2","type":"Artifact","subType":null,"power":null,"toughness":null,"abilities":"{tap}: Add to your mana pool one mana of any color that a land an opponent controls could produce.","implemented":true,"requested":false,"tested":false,"bugged":false,"developer":null,"editions":[{"rarity":"Uncommon","gathererId":"1714","mtgoImageId":"00765","expansionCode":"DK","expansionName":"The Dark","cardNumber":"99"},{"rarity":"Uncommon","gathererId":"2042","mtgoImageId":"00765","expansionCode":"4E","expansionName":"Fourth Edition","cardNumber":"337"},{"rarity":"Uncommon","gathererId":"3781","mtgoImageId":"00765","expansionCode":"5E","expansionName":"Fifth Edition","cardNumber":"369"},{"rarity":"Uncommon","gathererId":"83489","mtgoImageId":"86937","expansionCode":"9ED","expansionName":"Ninth Edition","cardNumber":"297"},{"rarity":"Common","gathererId":"201228","mtgoImageId":"00765","expansionCode":"ME3","expansionName":"Masters Edition III","cardNumber":"195"},{"rarity":"Uncommon","gathererId":"247152","mtgoImageId":"86937","expansionCode":"CMD","expansionName":"Magic: The Gathering-Commander","cardNumber":"248"},{"rarity":"Uncommon","gathererId":"405229","mtgoImageId":null,"expansionCode":"C15","expansionName":"Commander 2015","cardNumber":"254"},{"rarity":"Uncommon","gathererId":"420871","mtgoImageId":null,"expansionCode":"C16","expansionName":"Commander 2016","cardNumber":"254"},{"rarity":"Uncommon","gathererId":"433142","mtgoImageId":null,"expansionCode":"C17","expansionName":"Commander 2017","cardNumber":"210"}],"otherSide":null},{"id":7524,"name":"Coral Eel","cost":"1$U","type":"Creature","subType":"Fish","power":"2","toughness":"1","abilities":"","implemented":true,"requested":false,"tested":false,"bugged":false,"developer":null,"editions":[{"rarity":"Common","gathererId":"4256","mtgoImageId":"06612","expansionCode":"PO","expansionName":"Portal","cardNumber":"50"},{"rarity":"Common","gathererId":"21025","mtgoImageId":null,"expansionCode":"P3","expansionName":"Starter 1999","cardNumber":"33"},{"rarity":"Common","gathererId":"45247","mtgoImageId":"06612","expansionCode":"8ED","expansionName":"Eighth Edition","cardNumber":"70"},{"rarity":"Common","gathererId":"84073","mtgoImageId":"06612","expansionCode":"9ED","expansionName":"Ninth Edition","cardNumber":"3"}],"otherSide":null},{"id":7525,"name":"Oracle's Attendants","cost":"3$W","type":"Creature","subType":"Human Soldier","power":"1","toughness":"5","abilities":"{tap}: All damage that would be dealt to target creature this turn by a source of your choice is dealt to Oracle's Attendants instead.","implemented":true,"requested":false,"tested":false,"bugged":false,"developer":null,"editions":[{"rarity":"Rare","gathererId":"22030","mtgoImageId":"21193","expansionCode":"NE","expansionName":"Nemesis","cardNumber":"16"},{"rarity":"Rare","gathererId":"45210","mtgoImageId":"21193","expansionCode":"8ED","expansionName":"Eighth Edition","cardNumber":"32"},{"rarity":"Rare","gathererId":"83192","mtgoImageId":"21193","expansionCode":"9ED","expansionName":"Ninth Edition","cardNumber":"30"}],"otherSide":null},{"id":7526,"name":"Jade Statue","cost":"4","type":"Artifact","subType":null,"power":null,"toughness":null,"abilities":"{2}: Jade Statue becomes a 3/6 Golem artifact creature until end of combat. Activate this ability only during combat.","implemented":true,"requested":false,"tested":false,"bugged":false,"developer":null,"editions":[{"rarity":"Uncommon","gathererId":"24","mtgoImageId":"00132","expansionCode":"1E","expansionName":"Limited Edition Alpha","cardNumber":"253"},{"rarity":"Uncommon","gathererId":"319","mtgoImageId":"00132","expansionCode":"2E","expansionName":"Limited Edition Beta","cardNumber":"255"},{"rarity":"Uncommon","gathererId":"621","mtgoImageId":"00132","expansionCode":"2U","expansionName":"Unlimited Edition","cardNumber":"254"},{"rarity":"Rare","gathererId":"83350","mtgoImageId":"86929","expansionCode":"9ED","expansionName":"Ninth Edition","cardNumber":"300"}],"otherSide":null},{"id":7527,"name":"Jester's Cap","cost":"4","type":"Artifact","subType":null,"power":null,"toughness":null,"abilities":"{2}, {tap}, Sacrifice Jester's Cap: Search target player's library for three cards and exile them. Then that player shuffles his or her library.","implemented":true,"requested":false,"tested":false,"bugged":false,"developer":null,"editions":[{"rarity":"Rare","gathererId":"2410","mtgoImageId":"01233","expansionCode":"IA","expansionName":"Ice Age","cardNumber":"299"},{"rarity":"Rare","gathererId":"3797","mtgoImageId":"01233","expansionCode":"5E","expansionName":"Fifth Edition","cardNumber":"385"},{"rarity":"Rare","gathererId":"84595","mtgoImageId":"86955","expansionCode":"9ED","expansionName":"Ninth Edition","cardNumber":"301"}],"otherSide":null},{"id":7528,"name":"Slate of Ancestry","cost":"4","type":"Artifact","subType":null,"power":null,"toughness":null,"abilities":"{4}, {tap}, Discard your hand: Draw a card for each creature you control.","implemented":true,"requested":false,"tested":false,"bugged":false,"developer":null,"editions":[{"rarity":"Rare","gathererId":"39696","mtgoImageId":"43209","expansionCode":"ONS","expansionName":"Onslaught","cardNumber":"310"},{"rarity":"Rare","gathererId":"83540","mtgoImageId":"43209","expansionCode":"9ED","expansionName":"Ninth Edition","cardNumber":"308"},{"rarity":"Rare","gathererId":"159501","mtgoImageId":"43209","expansionCode":"EVG","expansionName":"Duel Decks: Elves vs. Goblins","cardNumber":"25"}],"otherSide":null},{"id":7529,"name":"Storage Matrix","cost":"3","type":"Artifact","subType":null,"power":null,"toughness":null,"abilities":"As long as Storage Matrix is untapped, each player chooses artifact, creature, or land during his or her untap step. That player can untap only permanents of the chosen type this step.","implemented":true,"requested":false,"tested":false,"bugged":false,"developer":null,"editions":[{"rarity":"Rare","gathererId":"15260","mtgoImageId":"16334","expansionCode":"CG","expansionName":"Urza's Destiny","cardNumber":"138"},{"rarity":"Rare","gathererId":"84652","mtgoImageId":"16334","expansionCode":"9ED","expansionName":"Ninth Edition","cardNumber":"310"}],"otherSide":null},{"id":7530,"name":"Teferi's Puzzle Box","cost":"4","type":"Artifact","subType":null,"power":null,"toughness":null,"abilities":"At the beginning of each player's draw step, that player puts the cards in his or her hand on the bottom of his or her library in any order, then draws that many cards.","implemented":true,"requested":false,"tested":false,"bugged":false,"developer":null,"editions":[{"rarity":"Rare","gathererId":"3604","mtgoImageId":"02271","expansionCode":"VI","expansionName":"Visions","cardNumber":"156"},{"rarity":"Rare","gathererId":"15410","mtgoImageId":"02271","expansionCode":"6E","expansionName":"Sixth Edition","cardNumber":"314"},{"rarity":"Rare","gathererId":"25662","mtgoImageId":"27826","expansionCode":"7E","expansionName":"Seventh Edition","cardNumber":"321"},{"rarity":"Rare","gathererId":"45483","mtgoImageId":"27826","expansionCode":"8ED","expansionName":"Eighth Edition","cardNumber":"316"},{"rarity":"Rare","gathererId":"83294","mtgoImageId":"27826","expansionCode":"9ED","expansionName":"Ninth Edition","cardNumber":"312"}],"otherSide":null},{"id":7531,"name":"Urza's Mine","cost":"","type":"Land","subType":"Urza’s Mine","power":null,"toughness":null,"abilities":"{tap}: Add {1} to your mana pool. If you control an Urza's Power-Plant and an Urza's Tower, add {2} to your mana pool instead.","implemented":true,"requested":false,"tested":false,"bugged":false,"developer":null,"editions":[{"rarity":"Common","gathererId":"1080","mtgoImageId":"00462","expansionCode":"AQ","expansionName":"Antiquities","cardNumber":"75"},{"rarity":"Common","gathererId":"4192","mtgoImageId":"00462","expansionCode":"5E","expansionName":"Fifth Edition","cardNumber":"447"},{"rarity":"Uncommon","gathererId":"45464","mtgoImageId":"49255","expansionCode":"8ED","expansionName":"Eighth Edition","cardNumber":"328"},{"rarity":"Uncommon","gathererId":"83314","mtgoImageId":"86936","expansionCode":"9ED","expansionName":"Ninth Edition","cardNumber":"327"},{"rarity":"BasicLand","gathererId":"220947","mtgoImageId":"00465","expansionCode":"ME4","expansionName":"Masters Edition IV","cardNumber":"257"}],"otherSide":null},{"id":7532,"name":"Urza's Power Plant","cost":"","type":"Land","subType":"Urza’s Power-Plant","power":null,"toughness":null,"abilities":"{tap}: Add {1} to your mana pool. If you control an Urza's Mine and an Urza's Tower, add {2} to your mana pool instead.","implemented":true,"requested":false,"tested":false,"bugged":false,"developer":null,"editions":[{"rarity":"Uncommon","gathererId":"1084","mtgoImageId":"00469","expansionCode":"AQ","expansionName":"Antiquities","cardNumber":"79"},{"rarity":"Common","gathererId":"4193","mtgoImageId":"00468","expansionCode":"5E","expansionName":"Fifth Edition","cardNumber":"448"},{"rarity":"Uncommon","gathererId":"45470","mtgoImageId":"49259","expansionCode":"8ED","expansionName":"Eighth Edition","cardNumber":"329"},{"rarity":"Uncommon","gathererId":"83315","mtgoImageId":"49259","expansionCode":"9ED","expansionName":"Ninth Edition","cardNumber":"328"},{"rarity":"BasicLand","gathererId":"220951","mtgoImageId":"00470","expansionCode":"ME4","expansionName":"Masters Edition IV","cardNumber":"258"}],"otherSide":null},{"id":7533,"name":"Urza's Tower","cost":"","type":"Land","subType":"Urza’s Tower","power":null,"toughness":null,"abilities":"{tap}: Add {1} to your mana pool. If you control an Urza's Mine and an Urza's Power-Plant, add {3} to your mana pool instead.","implemented":true,"requested":false,"tested":false,"bugged":false,"developer":null,"editions":[{"rarity":"Uncommon","gathererId":"1088","mtgoImageId":"00473","expansionCode":"AQ","expansionName":"Antiquities","cardNumber":"83"},{"rarity":"Common","gathererId":"4194","mtgoImageId":"00471","expansionCode":"5E","expansionName":"Fifth Edition","cardNumber":"449"},{"rarity":"Uncommon","gathererId":"45468","mtgoImageId":"49258","expansionCode":"8ED","expansionName":"Eighth Edition","cardNumber":"330"},{"rarity":"Uncommon","gathererId":"83316","mtgoImageId":"49258","expansionCode":"9ED","expansionName":"Ninth Edition","cardNumber":"329"},{"rarity":"BasicLand","gathererId":"220955","mtgoImageId":"00471","expansionCode":"ME4","expansionName":"Masters Edition IV","cardNumber":"259"}],"otherSide":null},{"id":7534,"name":"Peace of Mind","cost":"1$W","type":"Enchantment","subType":null,"power":null,"toughness":null,"abilities":"{W}, Discard a card: You gain 3 life.","implemented":true,"requested":false,"tested":false,"bugged":false,"developer":null,"editions":[{"rarity":"Uncommon","gathererId":"6039","mtgoImageId":"05429","expansionCode":"EX","expansionName":"Exodus","cardNumber":"13"},{"rarity":"Uncommon","gathererId":"84697","mtgoImageId":"05429","expansionCode":"9ED","expansionName":"Ninth Edition","cardNumber":"33"},{"rarity":"Uncommon","gathererId":"414328","mtgoImageId":null,"expansionCode":"EMN","expansionName":"Eldritch Moon","cardNumber":"36"}],"otherSide":null},{"id":7535,"name":"Reverse Damage","cost":"1$W$W","type":"Instant","subType":null,"power":null,"toughness":null,"abilities":"The next time a source of your choice would deal damage to you this turn, prevent that damage. You gain life equal to the damage prevented this way.","implemented":true,"requested":false,"tested":false,"bugged":false,"developer":null,"editions":[{"rarity":"Rare","gathererId":"266","mtgoImageId":"00208","expansionCode":"1E","expansionName":"Limited Edition Alpha","cardNumber":"219"},{"rarity":"Rare","gathererId":"562","mtgoImageId":"00208","expansionCode":"2E","expansionName":"Limited Edition Beta","cardNumber":"221"},{"rarity":"Rare","gathererId":"864","mtgoImageId":"00208","expansionCode":"2U","expansionName":"Unlimited Edition","cardNumber":"220"},{"rarity":"Rare","gathererId":"1361","mtgoImageId":"00208","expansionCode":"3E","expansionName":"Revised Edition","cardNumber":"219"},{"rarity":"Rare","gathererId":"2360","mtgoImageId":"00208","expansionCode":"4E","expansionName":"Fourth Edition","cardNumber":"295"},{"rarity":"Rare","gathererId":"4152","mtgoImageId":"02461","expansionCode":"5E","expansionName":"Fifth Edition","cardNumber":"331"},{"rarity":"Rare","gathererId":"11472","mtgoImageId":"02461","expansionCode":"6E","expansionName":"Sixth Edition","cardNumber":"39"},{"rarity":"Rare","gathererId":"15799","mtgoImageId":"27766","expansionCode":"7E","expansionName":"Seventh Edition","cardNumber":"34"},{"rarity":"Rare","gathererId":"83132","mtgoImageId":"02461","expansionCode":"9ED","expansionName":"Ninth Edition","cardNumber":"35"}],"otherSide":null},{"id":7536,"name":"Sacred Ground","cost":"1$W","type":"Enchantment","subType":null,"power":null,"toughness":null,"abilities":"Whenever a spell or ability an opponent controls causes a land to be put into your graveyard from the battlefield, return that card to the battlefield.","implemented":true,"requested":false,"tested":false,"bugged":false,"developer":null,"editions":[{"rarity":"Rare","gathererId":"5214","mtgoImageId":"03748","expansionCode":"ST","expansionName":"Stronghold","cardNumber":"112"},{"rarity":"Rare","gathererId":"25551","mtgoImageId":"27771","expansionCode":"7E","expansionName":"Seventh Edition","cardNumber":"36"},{"rarity":"Rare","gathererId":"45215","mtgoImageId":"27771","expansionCode":"8ED","expansionName":"Eighth Edition","cardNumber":"39"},{"rarity":"Rare","gathererId":"83239","mtgoImageId":"27771","expansionCode":"9ED","expansionName":"Ninth Edition","cardNumber":"37"}],"otherSide":null},{"id":7537,"name":"Sacred Nectar","cost":"1$W","type":"Sorcery","subType":null,"power":null,"toughness":null,"abilities":"You gain 4 life.","implemented":true,"requested":false,"tested":false,"bugged":false,"developer":null,"editions":[{"rarity":"Common","gathererId":"4393","mtgoImageId":"06748","expansionCode":"PO","expansionName":"Portal","cardNumber":"187"},{"rarity":"Common","gathererId":"21061","mtgoImageId":null,"expansionCode":"P3","expansionName":"Starter 1999","cardNumber":"26"},{"rarity":"Common","gathererId":"30168","mtgoImageId":"31242","expansionCode":"7E","expansionName":"Seventh Edition","cardNumber":"37"},{"rarity":"Common","gathererId":"45187","mtgoImageId":"06748","expansionCode":"8ED","expansionName":"Eighth Edition","cardNumber":"40"},{"rarity":"Common","gathererId":"83240","mtgoImageId":"06748","expansionCode":"9ED","expansionName":"Ninth Edition","cardNumber":"38"}],"otherSide":null},{"id":7538,"name":"Aven Flock","cost":"4$W","type":"Creature","subType":"Bird Soldier","power":"2","toughness":"3","abilities":"Flying <i>(This creature can't be blocked except by creatures with flying or reach.)</i>${W}: Aven Flock gets +0/+1 until end of turn.","implemented":true,"requested":false,"tested":false,"bugged":false,"developer":null,"editions":[{"rarity":"Common","gathererId":"31767","mtgoImageId":"33476","expansionCode":"OD","expansionName":"Odyssey","cardNumber":"8"},{"rarity":"Common","gathererId":"45179","mtgoImageId":"33476","expansionCode":"8ED","expansionName":"Eighth Edition","cardNumber":"6"},{"rarity":"Common","gathererId":"82999","mtgoImageId":"33476","expansionCode":"9ED","expansionName":"Ninth Edition","cardNumber":"4"}],"otherSide":null},{"id":7539,"name":"Giant Octopus","cost":"3$U","type":"Creature","subType":"Octopus","power":"3","toughness":"3","abilities":"","implemented":true,"requested":false,"tested":false,"bugged":false,"developer":null,"editions":[{"rarity":"Common","gathererId":"4263","mtgoImageId":"06619","expansionCode":"PO","expansionName":"Portal","cardNumber":"57"},{"rarity":"Common","gathererId":"21027","mtgoImageId":null,"expansionCode":"P3","expansionName":"Starter 1999","cardNumber":"39"},{"rarity":"Common","gathererId":"25457","mtgoImageId":null,"expansionCode":"P4","expansionName":"Starter 2000","cardNumber":"5"},{"rarity":"Common","gathererId":"30170","mtgoImageId":"31243","expansionCode":"7E","expansionName":"Seventh Edition","cardNumber":"77"},{"rarity":"Common","gathererId":"47785","mtgoImageId":"31243","expansionCode":"8ED","expansionName":"Eighth Edition","cardNumber":"3"},{"rarity":"Common","gathererId":"83104","mtgoImageId":"31243","expansionCode":"9ED","expansionName":"Ninth Edition","cardNumber":"4"}],"otherSide":null},{"id":7540,"name":"Savannah Lions","cost":"W","type":"Creature","subType":"Cat","power":"2","toughness":"1","abilities":"","implemented":true,"requested":false,"tested":false,"bugged":false,"developer":null,"editions":[{"rarity":"Rare","gathererId":"269","mtgoImageId":"00217","expansionCode":"1E","expansionName":"Limited Edition Alpha","cardNumber":"222"},{"rarity":"Rare","gathererId":"565","mtgoImageId":"00217","expansionCode":"2E","expansionName":"Limited Edition Beta","cardNumber":"224"},{"rarity":"Rare","gathererId":"867","mtgoImageId":"00217","expansionCode":"2U","expansionName":"Unlimited Edition","cardNumber":"223"},{"rarity":"Rare","gathererId":"1365","mtgoImageId":"00217","expansionCode":"3E","expansionName":"Revised Edition","cardNumber":"223"},{"rarity":"Rare","gathererId":"2363","mtgoImageId":"00217","expansionCode":"4E","expansionName":"Fourth Edition","cardNumber":"298"},{"rarity":"Rare","gathererId":"45207","mtgoImageId":"49228","expansionCode":"8ED","expansionName":"Eighth Edition","cardNumber":"43"},{"rarity":"Rare","gathererId":"83246","mtgoImageId":"49228","expansionCode":"9ED","expansionName":"Ninth Edition","cardNumber":"41"},{"rarity":"Uncommon","gathererId":"221577","mtgoImageId":"00217","expansionCode":"ME4","expansionName":"Masters Edition IV","cardNumber":"24"}],"otherSide":null},{"id":7541,"name":"Serra's Blessing","cost":"1$W","type":"Enchantment","subType":null,"power":null,"toughness":null,"abilities":"Creatures you control have vigilance. <i>(Attacking doesn't cause them to tap.)</i>","implemented":true,"requested":false,"tested":false,"bugged":false,"developer":null,"editions":[{"rarity":"Uncommon","gathererId":"4587","mtgoImageId":"02958","expansionCode":"WL","expansionName":"Weatherlight","cardNumber":"141"},{"rarity":"Uncommon","gathererId":"14476","mtgoImageId":"02958","expansionCode":"6E","expansionName":"Sixth Edition","cardNumber":"42"},{"rarity":"Uncommon","gathererId":"82964","mtgoImageId":"02958","expansionCode":"9ED","expansionName":"Ninth Edition","cardNumber":"44"}],"otherSide":null},{"id":7542,"name":"Veteran Cavalier","cost":"W$W","type":"Creature","subType":"Human Knight","power":"2","toughness":"2","abilities":"Vigilance <i>(Attacking doesn't cause this creature to tap.)</i>","implemented":true,"requested":false,"tested":false,"bugged":false,"developer":null,"editions":[{"rarity":"Uncommon","gathererId":"20403","mtgoImageId":null,"expansionCode":"P3","expansionName":"Starter 1999","cardNumber":"30"},{"rarity":"Common","gathererId":"84622","mtgoImageId":"17559","expansionCode":"9ED","expansionName":"Ninth Edition","cardNumber":"52"}],"otherSide":null},{"id":7543,"name":"Weathered Wayfarer","cost":"W","type":"Creature","subType":"Human Nomad Cleric","power":"1","toughness":"1","abilities":"{W}, {tap}: Search your library for a land card, reveal it, and put it into your hand. Then shuffle your library. Activate this ability only if an opponent controls more lands than you.","implemented":true,"requested":false,"tested":false,"bugged":false,"developer":null,"editions":[{"rarity":"Rare","gathererId":"39515","mtgoImageId":"42957","expansionCode":"ONS","expansionName":"Onslaught","cardNumber":"59"},{"rarity":"Rare","gathererId":"83311","mtgoImageId":"42957","expansionCode":"9ED","expansionName":"Ninth Edition","cardNumber":"54"}],"otherSide":null},{"id":7544,"name":"Zealous Inquisitor","cost":"2$W","type":"Creature","subType":"Human Cleric","power":"2","toughness":"2","abilities":"{1}{W}: The next 1 damage that would be dealt to Zealous Inquisitor this turn is dealt to target creature instead.","implemented":true,"requested":false,"tested":false,"bugged":false,"developer":null,"editions":[{"rarity":"Common","gathererId":"42040","mtgoImageId":"49046","expansionCode":"SCG","expansionName":"Scourge","cardNumber":"27"},{"rarity":"Uncommon","gathererId":"84122","mtgoImageId":"49046","expansionCode":"9ED","expansionName":"Ninth Edition","cardNumber":"57"}],"otherSide":null},{"id":7545,"name":"Annex","cost":"2$U$U","type":"Enchantment","subType":"Aura","power":null,"toughness":null,"abilities":"Enchant land <i>(Target a land as you cast this. This card enters the battlefield attached to that land.)</i>$You control enchanted land.","implemented":true,"requested":false,"tested":false,"bugged":false,"developer":null,"editions":[{"rarity":"Uncommon","gathererId":"41463","mtgoImageId":"42994","expansionCode":"ONS","expansionName":"Onslaught","cardNumber":"63"},{"rarity":"Uncommon","gathererId":"84564","mtgoImageId":"42994","expansionCode":"9ED","expansionName":"Ninth Edition","cardNumber":"59"}],"otherSide":null},{"id":7546,"name":"Blessed Orator","cost":"3$W","type":"Creature","subType":"Human Cleric","power":"1","toughness":"4","abilities":"Other creatures you control get +0/+1.","implemented":true,"requested":false,"tested":false,"bugged":false,"developer":null,"editions":[{"rarity":"Uncommon","gathererId":"29688","mtgoImageId":"33534","expansionCode":"OD","expansionName":"Odyssey","cardNumber":"12"},{"rarity":"Uncommon","gathererId":"84057","mtgoImageId":"33534","expansionCode":"9ED","expansionName":"Ninth Edition","cardNumber":"6"}],"otherSide":null},{"id":7547,"name":"Archivist","cost":"2$U$U","type":"Creature","subType":"Human Wizard","power":"1","toughness":"1","abilities":"{tap}: Draw a card.","implemented":true,"requested":false,"tested":false,"bugged":false,"developer":null,"editions":[{"rarity":"Rare","gathererId":"12390","mtgoImageId":"10413","expansionCode":"GU","expansionName":"Urza's Legacy","cardNumber":"26"},{"rarity":"Rare","gathererId":"13157","mtgoImageId":"27537","expansionCode":"7E","expansionName":"Seventh Edition","cardNumber":"61"},{"rarity":"Rare","gathererId":"45268","mtgoImageId":"27537","expansionCode":"8ED","expansionName":"Eighth Edition","cardNumber":"60"},{"rarity":"Rare","gathererId":"82994","mtgoImageId":"27537","expansionCode":"9ED","expansionName":"Ninth Edition","cardNumber":"60"}],"otherSide":null},{"id":7548,"name":"Baleful Stare","cost":"2$U","type":"Sorcery","subType":null,"power":null,"toughness":null,"abilities":"Target opponent reveals his or her hand. You draw a card for each Mountain and red card in it.","implemented":true,"requested":false,"tested":false,"bugged":false,"developer":null,"editions":[{"rarity":"Uncommon","gathererId":"4249","mtgoImageId":"06605","expansionCode":"PO","expansionName":"Portal","cardNumber":"43"},{"rarity":"Uncommon","gathererId":"13124","mtgoImageId":"27540","expansionCode":"7E","expansionName":"Seventh Edition","cardNumber":"62"},{"rarity":"Uncommon","gathererId":"84424","mtgoImageId":"86947","expansionCode":"9ED","expansionName":"Ninth Edition","cardNumber":"64"}],"otherSide":null},{"id":7549,"name":"Battle of Wits","cost":"3$U$U","type":"Enchantment","subType":null,"power":null,"toughness":null,"abilities":"At the beginning of your upkeep, if you have 200 or more cards in your library, you win the game.","implemented":true,"requested":false,"tested":false,"bugged":false,"developer":null,"editions":[{"rarity":"Rare","gathererId":"29942","mtgoImageId":"33445","expansionCode":"OD","expansionName":"Odyssey","cardNumber":"69"},{"rarity":"Rare","gathererId":"83133","mtgoImageId":"86911","expansionCode":"9ED","expansionName":"Ninth Edition","cardNumber":"65"},{"rarity":"Rare","gathererId":"288878","mtgoImageId":"143933","expansionCode":"M13","expansionName":"Magic 2013","cardNumber":"44"}],"otherSide":null},{"id":7550,"name":"Blinding Angel","cost":"3$W$W","type":"Creature","subType":"Angel","power":"2","toughness":"4","abilities":"Flying <i>(This creature can't be blocked except by creatures with flying or reach.)</i>$Whenever Blinding Angel deals combat damage to a player, that player skips his or her next combat phase.","implemented":true,"requested":false,"tested":false,"bugged":false,"developer":null,"editions":[{"rarity":"Rare","gathererId":"21273","mtgoImageId":"21225","expansionCode":"NE","expansionName":"Nemesis","cardNumber":"3"},{"rarity":"Rare","gathererId":"45211","mtgoImageId":"21225","expansionCode":"8ED","expansionName":"Eighth Edition","cardNumber":"8"},{"rarity":"Rare","gathererId":"83007","mtgoImageId":"21225","expansionCode":"9ED","expansionName":"Ninth Edition","cardNumber":"7"}],"otherSide":null},{"id":7551,"name":"Vizzerdrix","cost":"6$U","type":"Creature","subType":"Rabbit Beast","power":"6","toughness":"6","abilities":"","implemented":true,"requested":false,"tested":false,"bugged":false,"developer":null,"editions":[{"rarity":"Rare","gathererId":"20188","mtgoImageId":null,"expansionCode":"P3","expansionName":"Starter 1999","cardNumber":"59"},{"rarity":"Rare","gathererId":"25463","mtgoImageId":null,"expansionCode":"P4","expansionName":"Starter 2000","cardNumber":"18"},{"rarity":"Rare","gathererId":"29322","mtgoImageId":"31220","expansionCode":"7E","expansionName":"Seventh Edition","cardNumber":"110"},{"rarity":"Rare","gathererId":"47789","mtgoImageId":"31220","expansionCode":"8ED","expansionName":"Eighth Edition","cardNumber":"5"},{"rarity":"Rare","gathererId":"94911","mtgoImageId":"31220","expansionCode":"9ED","expansionName":"Ninth Edition","cardNumber":"7"}],"otherSide":null},{"id":7552,"name":"Cowardice","cost":"3$U$U","type":"Enchantment","subType":null,"power":null,"toughness":null,"abilities":"Whenever a creature becomes the target of a spell or ability, return that creature to its owner's hand. <i>(It won't be affected by the spell or ability.)</i>","implemented":true,"requested":false,"tested":false,"bugged":false,"developer":null,"editions":[{"rarity":"Rare","gathererId":"19683","mtgoImageId":"19075","expansionCode":"MM","expansionName":"Mercadian Masques","cardNumber":"70"},{"rarity":"Rare","gathererId":"45280","mtgoImageId":"19075","expansionCode":"8ED","expansionName":"Eighth Edition","cardNumber":"71"},{"rarity":"Rare","gathererId":"83039","mtgoImageId":"87021","expansionCode":"9ED","expansionName":"Ninth Edition","cardNumber":"70"}],"otherSide":null},{"id":7553,"name":"Daring Apprentice","cost":"1$U$U","type":"Creature","subType":"Human Wizard","power":"1","toughness":"1","abilities":"{tap}, Sacrifice Daring Apprentice: Counter target spell.","implemented":true,"requested":false,"tested":false,"bugged":false,"developer":null,"editions":[{"rarity":"Rare","gathererId":"3331","mtgoImageId":"01845","expansionCode":"MI","expansionName":"Mirage","cardNumber":"60"},{"rarity":"Rare","gathererId":"14552","mtgoImageId":"01845","expansionCode":"6E","expansionName":"Sixth Edition","cardNumber":"62"},{"rarity":"Rare","gathererId":"12960","mtgoImageId":"27584","expansionCode":"7E","expansionName":"Seventh Edition","cardNumber":"68"},{"rarity":"Rare","gathererId":"45267","mtgoImageId":"27584","expansionCode":"8ED","expansionName":"Eighth Edition","cardNumber":"73"},{"rarity":"Rare","gathererId":"82942","mtgoImageId":"27584","expansionCode":"9ED","expansionName":"Ninth Edition","cardNumber":"72"}],"otherSide":null},{"id":7554,"name":"Dream Prowler","cost":"2$U$U","type":"Creature","subType":"Illusion","power":"1","toughness":"5","abilities":"Dream Prowler can't be blocked as long as it's attacking alone.","implemented":true,"requested":false,"tested":false,"bugged":false,"developer":null,"editions":[{"rarity":"Common","gathererId":"5140","mtgoImageId":"03674","expansionCode":"ST","expansionName":"Stronghold","cardNumber":"29"},{"rarity":"Uncommon","gathererId":"83258","mtgoImageId":"86922","expansionCode":"9ED","expansionName":"Ninth Edition","cardNumber":"74"},{"rarity":"Uncommon","gathererId":"397558","mtgoImageId":"03674","expansionCode":"TPR","expansionName":"Tempest Remastered","cardNumber":"47"}],"otherSide":null},{"id":7555,"name":"Fishliver Oil","cost":"1$U","type":"Enchantment","subType":"Aura","power":null,"toughness":null,"abilities":"Enchant creature <i>(Target a creature as you cast this. This card enters the battlefield attached to that creature.)</i>$Enchanted creature has islandwalk. <i>(It can't be blocked as long as defending player controls an Island.)</i>","implemented":true,"requested":false,"tested":false,"bugged":false,"developer":null,"editions":[{"rarity":"Common","gathererId":"930","mtgoImageId":"00332","expansionCode":"AN","expansionName":"Arabian Nights","cardNumber":"17"},{"rarity":"Common","gathererId":"83438","mtgoImageId":"86934","expansionCode":"9ED","expansionName":"Ninth Edition","cardNumber":"77"}],"otherSide":null},{"id":7556,"name":"Fleeting Image","cost":"2$U","type":"Creature","subType":"Illusion","power":"2","toughness":"1","abilities":"Flying <i>(This creature can't be blocked except by creatures with flying or reach.)</i>${1}{U}: Return Fleeting Image to its owner's hand.","implemented":true,"requested":false,"tested":false,"bugged":false,"developer":null,"editions":[{"rarity":"Rare","gathererId":"12389","mtgoImageId":"10355","expansionCode":"GU","expansionName":"Urza's Legacy","cardNumber":"31"},{"rarity":"Rare","gathererId":"13156","mtgoImageId":"27619","expansionCode":"7E","expansionName":"Seventh Edition","cardNumber":"74"},{"rarity":"Rare","gathererId":"45265","mtgoImageId":"27619","expansionCode":"8ED","expansionName":"Eighth Edition","cardNumber":"79"},{"rarity":"Rare","gathererId":"83087","mtgoImageId":"27619","expansionCode":"9ED","expansionName":"Ninth Edition","cardNumber":"78"}],"otherSide":null},{"id":7557,"name":"Blinking Spirit","cost":"3$W","type":"Creature","subType":"Spirit","power":"2","toughness":"2","abilities":"{0}: Return Blinking Spirit to its owner's hand.","implemented":true,"requested":false,"tested":false,"bugged":false,"developer":null,"editions":[{"rarity":"Rare","gathererId":"2668","mtgoImageId":"01091","expansionCode":"IA","expansionName":"Ice Age","cardNumber":"232"},{"rarity":"Rare","gathererId":"4109","mtgoImageId":"02316","expansionCode":"5E","expansionName":"Fifth Edition","cardNumber":"288"},{"rarity":"Rare","gathererId":"83962","mtgoImageId":"02316","expansionCode":"9ED","expansionName":"Ninth Edition","cardNumber":"8"}],"otherSide":null},{"id":7558,"name":"Chastise","cost":"3$W","type":"Instant","subType":null,"power":null,"toughness":null,"abilities":"Destroy target attacking creature. You gain life equal to its power.","implemented":true,"requested":false,"tested":false,"bugged":false,"developer":null,"editions":[{"rarity":"Uncommon","gathererId":"34958","mtgoImageId":"41059","expansionCode":"JUD","expansionName":"Judgment","cardNumber":"8"},{"rarity":"Uncommon","gathererId":"45200","mtgoImageId":"41059","expansionCode":"8ED","expansionName":"Eighth Edition","cardNumber":"9"},{"rarity":"Uncommon","gathererId":"83021","mtgoImageId":"41059","expansionCode":"9ED","expansionName":"Ninth Edition","cardNumber":"9"}],"otherSide":null},{"id":7559,"name":"Sage Aven","cost":"3$U","type":"Creature","subType":"Bird Wizard","power":"1","toughness":"3","abilities":"Flying <i>(This creature can't be blocked except by creatures with flying or reach.)</i>$When Sage Aven enters the battlefield, look at the top four cards of your library, then put them back in any order.","implemented":true,"requested":false,"tested":false,"bugged":false,"developer":null,"editions":[{"rarity":"Common","gathererId":"39440","mtgoImageId":"42921","expansionCode":"ONS","expansionName":"Onslaught","cardNumber":"111"},{"rarity":"Common","gathererId":"83985","mtgoImageId":"42921","expansionCode":"9ED","expansionName":"Ninth Edition","cardNumber":"95"}],"otherSide":null},{"id":7560,"name":"Sea's Claim","cost":"U","type":"Enchantment","subType":"Aura","power":null,"toughness":null,"abilities":"Enchant land <i>(Target a land as you cast this. This card enters the battlefield attached to that land.)</i>$Enchanted land is an Island.","implemented":true,"requested":false,"tested":false,"bugged":false,"developer":null,"editions":[{"rarity":"Common","gathererId":"39446","mtgoImageId":"42984","expansionCode":"ONS","expansionName":"Onslaught","cardNumber":"113"},{"rarity":"Common","gathererId":"83446","mtgoImageId":"86935","expansionCode":"9ED","expansionName":"Ninth Edition","cardNumber":"97"}],"otherSide":null},{"id":7561,"name":"Sleight of Hand","cost":"U","type":"Sorcery","subType":null,"power":null,"toughness":null,"abilities":"Look at the top two cards of your library. Put one of them into your hand and the other on the bottom of your library.","implemented":true,"requested":false,"tested":false,"bugged":false,"developer":null,"editions":[{"rarity":"Common","gathererId":"6529","mtgoImageId":"04636","expansionCode":"P2","expansionName":"Portal Second Age","cardNumber":"46"},{"rarity":"Common","gathererId":"21068","mtgoImageId":null,"expansionCode":"P3","expansionName":"Starter 1999","cardNumber":"51"},{"rarity":"Common","gathererId":"25557","mtgoImageId":"27793","expansionCode":"7E","expansionName":"Seventh Edition","cardNumber":"98"},{"rarity":"Common","gathererId":"83129","mtgoImageId":"86910","expansionCode":"9ED","expansionName":"Ninth Edition","cardNumber":"99"},{"rarity":"Common","gathererId":"221496","mtgoImageId":"04636","expansionCode":"ME4","expansionName":"Masters Edition IV","cardNumber":"62"}],"otherSide":null},{"id":7562,"name":"Sneaky Homunculus","cost":"1$U","type":"Creature","subType":"Homunculus Illusion","power":"1","toughness":"1","abilities":"Sneaky Homunculus can't block or be blocked by creatures with power 2 or greater.","implemented":true,"requested":false,"tested":false,"bugged":false,"developer":null,"editions":[{"rarity":"Common","gathererId":"21282","mtgoImageId":"21203","expansionCode":"NE","expansionName":"Nemesis","cardNumber":"44"},{"rarity":"Common","gathererId":"45228","mtgoImageId":"21203","expansionCode":"8ED","expansionName":"Eighth Edition","cardNumber":"101"}],"otherSide":null},{"id":7563,"name":"Steal Artifact","cost":"2$U$U","type":"Enchantment","subType":"Aura","power":null,"toughness":null,"abilities":"Enchant artifact$You control enchanted artifact.","implemented":true,"requested":false,"tested":false,"bugged":false,"developer":null,"editions":[{"rarity":"Uncommon","gathererId":"129","mtgoImageId":"00238","expansionCode":"1E","expansionName":"Limited Edition Alpha","cardNumber":"82"},{"rarity":"Uncommon","gathererId":"424","mtgoImageId":"00238","expansionCode":"2E","expansionName":"Limited Edition Beta","cardNumber":"82"},{"rarity":"Uncommon","gathererId":"726","mtgoImageId":"00238","expansionCode":"2U","expansionName":"Unlimited Edition","cardNumber":"82"},{"rarity":"Uncommon","gathererId":"1226","mtgoImageId":"00238","expansionCode":"3E","expansionName":"Revised Edition","cardNumber":"84"},{"rarity":"Uncommon","gathererId":"2188","mtgoImageId":"00238","expansionCode":"4E","expansionName":"Fourth Edition","cardNumber":"105"},{"rarity":"Uncommon","gathererId":"3949","mtgoImageId":"02483","expansionCode":"5E","expansionName":"Fifth Edition","cardNumber":"128"},{"rarity":"Uncommon","gathererId":"15801","mtgoImageId":"27808","expansionCode":"7E","expansionName":"Seventh Edition","cardNumber":"99"},{"rarity":"Uncommon","gathererId":"45263","mtgoImageId":"27808","expansionCode":"8ED","expansionName":"Eighth Edition","cardNumber":"103"}],"otherSide":null},{"id":7564,"name":"Twiddle","cost":"U","type":"Instant","subType":null,"power":null,"toughness":null,"abilities":"You may tap or untap target artifact, creature, or land.","implemented":true,"requested":false,"tested":false,"bugged":false,"developer":null,"editions":[{"rarity":"Common","gathererId":"133","mtgoImageId":"00261","expansionCode":"1E","expansionName":"Limited Edition Alpha","cardNumber":"86"},{"rarity":"Common","gathererId":"428","mtgoImageId":"00261","expansionCode":"2E","expansionName":"Limited Edition Beta","cardNumber":"86"},{"rarity":"Common","gathererId":"730","mtgoImageId":"00261","expansionCode":"2U","expansionName":"Unlimited Edition","cardNumber":"86"},{"rarity":"Common","gathererId":"2192","mtgoImageId":"00261","expansionCode":"4E","expansionName":"Fourth Edition","cardNumber":"109"},{"rarity":"Common","gathererId":"3951","mtgoImageId":"00261","expansionCode":"5E","expansionName":"Fifth Edition","cardNumber":"130"},{"rarity":"Common","gathererId":"11544","mtgoImageId":"27843","expansionCode":"7E","expansionName":"Seventh Edition","cardNumber":"107"},{"rarity":"Common","gathererId":"45235","mtgoImageId":"49229","expansionCode":"8ED","expansionName":"Eighth Edition","cardNumber":"111"}],"otherSide":null},{"id":7565,"name":"Wrath of Marit Lage","cost":"3$U$U","type":"Enchantment","subType":null,"power":null,"toughness":null,"abilities":"When Wrath of Marit Lage enters the battlefield, tap all red creatures.$Red creatures don't untap during their controllers' untap steps.","implemented":true,"requested":false,"tested":false,"bugged":false,"developer":null,"editions":[{"rarity":"Rare","gathererId":"2545","mtgoImageId":"01436","expansionCode":"IA","expansionName":"Ice Age","cardNumber":"109"},{"rarity":"Uncommon","gathererId":"45254","mtgoImageId":"49235","expansionCode":"8ED","expansionName":"Eighth Edition","cardNumber":"115"}],"otherSide":null},{"id":7566,"name":"Abyssal Specter","cost":"2$B$B","type":"Creature","subType":"Specter","power":"2","toughness":"3","abilities":"Flying$Whenever Abyssal Specter deals damage to a player, that player discards a card.","implemented":true,"requested":false,"tested":false,"bugged":false,"developer":null,"editions":[{"rarity":"Uncommon","gathererId":"2437","mtgoImageId":"01059","expansionCode":"IA","expansionName":"Ice Age","cardNumber":"1"},{"rarity":"Uncommon","gathererId":"3822","mtgoImageId":"02298","expansionCode":"5E","expansionName":"Fifth Edition","cardNumber":"1"},{"rarity":"Uncommon","gathererId":"15381","mtgoImageId":"02298","expansionCode":"6E","expansionName":"Sixth Edition","cardNumber":"110"},{"rarity":"Uncommon","gathererId":"25636","mtgoImageId":"27525","expansionCode":"7E","expansionName":"Seventh Edition","cardNumber":"116"},{"rarity":"Uncommon","gathererId":"45307","mtgoImageId":"27525","expansionCode":"8ED","expansionName":"Eighth Edition","cardNumber":"117"},{"rarity":"Uncommon","gathererId":"197008","mtgoImageId":"27525","expansionCode":"DDC","expansionName":"Duel Decks: Divine vs. Demonic","cardNumber":"40"},{"rarity":"Uncommon","gathererId":"425884","mtgoImageId":null,"expansionCode":"MM3","expansionName":"Modern Masters 2017 Edition","cardNumber":"59"}],"otherSide":null},{"id":7567,"name":"Ambition's Cost","cost":"3$B","type":"Sorcery","subType":null,"power":null,"toughness":null,"abilities":"You draw three cards and you lose 3 life.","implemented":true,"requested":false,"tested":false,"bugged":false,"developer":null,"editions":[{"rarity":"Rare","gathererId":"10493","mtgoImageId":"09141","expansionCode":"PK","expansionName":"Portal Three Kingdoms","cardNumber":"67"},{"rarity":"Uncommon","gathererId":"45313","mtgoImageId":"09141","expansionCode":"8ED","expansionName":"Eighth Edition","cardNumber":"118"},{"rarity":"Uncommon","gathererId":"405123","mtgoImageId":null,"expansionCode":"C15","expansionName":"Commander 2015","cardNumber":"113"},{"rarity":"Uncommon","gathererId":"417461","mtgoImageId":null,"expansionCode":"DDR","expansionName":"Duel Decks: Nissa vs. Ob Nixilis","cardNumber":"38"},{"rarity":"Uncommon","gathererId":"433027","mtgoImageId":null,"expansionCode":"C17","expansionName":"Commander 2017","cardNumber":"95"}],"otherSide":null},{"id":7568,"name":"Carrion Wall","cost":"1$B$B","type":"Creature","subType":"Wall","power":"3","toughness":"2","abilities":"Defender <i>(This creature can't attack.)</i>${1}{B}: Regenerate Carrion Wall.","implemented":true,"requested":false,"tested":false,"bugged":false,"developer":null,"editions":[{"rarity":"Uncommon","gathererId":"21319","mtgoImageId":"21267","expansionCode":"NE","expansionName":"Nemesis","cardNumber":"54"},{"rarity":"Uncommon","gathererId":"45306","mtgoImageId":"21267","expansionCode":"8ED","expansionName":"Eighth Edition","cardNumber":"121"}],"otherSide":null},{"id":7569,"name":"Death Pit Offering","cost":"2$B$B","type":"Enchantment","subType":null,"power":null,"toughness":null,"abilities":"When Death Pit Offering enters the battlefield, sacrifice all creatures you control.$Creatures you control get +2/+2.","implemented":true,"requested":false,"tested":false,"bugged":false,"developer":null,"editions":[{"rarity":"Rare","gathererId":"21330","mtgoImageId":"21278","expansionCode":"NE","expansionName":"Nemesis","cardNumber":"56"},{"rarity":"Rare","gathererId":"45338","mtgoImageId":"21278","expansionCode":"8ED","expansionName":"Eighth Edition","cardNumber":"124"}],"otherSide":null},{"id":7570,"name":"Deepwood Ghoul","cost":"2$B","type":"Creature","subType":"Zombie","power":"2","toughness":"1","abilities":"Pay 2 life: Regenerate Deepwood Ghoul.","implemented":true,"requested":false,"tested":false,"bugged":false,"developer":null,"editions":[{"rarity":"Common","gathererId":"19587","mtgoImageId":"19232","expansionCode":"MM","expansionName":"Mercadian Masques","cardNumber":"131"},{"rarity":"Common","gathererId":"45285","mtgoImageId":"19232","expansionCode":"8ED","expansionName":"Eighth Edition","cardNumber":"127"}],"otherSide":null},{"id":7571,"name":"Fallen Angel","cost":"3$B$B","type":"Creature","subType":"Angel","power":"3","toughness":"3","abilities":"Flying$Sacrifice a creature: Fallen Angel gets +2/+1 until end of turn.","implemented":true,"requested":false,"tested":false,"bugged":false,"developer":null,"editions":[{"rarity":"Uncommon","gathererId":"1437","mtgoImageId":"00552","expansionCode":"LE","expansionName":"Legends","cardNumber":"11"},{"rarity":"Uncommon","gathererId":"3844","mtgoImageId":"00552","expansionCode":"5E","expansionName":"Fifth Edition","cardNumber":"23"},{"rarity":"Rare","gathererId":"16629","mtgoImageId":"00552","expansionCode":"6E","expansionName":"Sixth Edition","cardNumber":"127"},{"rarity":"Rare","gathererId":"11268","mtgoImageId":"27609","expansionCode":"7E","expansionName":"Seventh Edition","cardNumber":"134"},{"rarity":"Rare","gathererId":"45330","mtgoImageId":"50349","expansionCode":"8ED","expansionName":"Eighth Edition","cardNumber":"133"},{"rarity":"Rare","gathererId":"197010","mtgoImageId":"50349","expansionCode":"DDC","expansionName":"Duel Decks: Divine vs. Demonic","cardNumber":"42"},{"rarity":"Rare","gathererId":"247150","mtgoImageId":"50349","expansionCode":"CMD","expansionName":"Magic: The Gathering-Commander","cardNumber":"82"}],"otherSide":null},{"id":7572,"name":"Larceny","cost":"3$B$B","type":"Enchantment","subType":null,"power":null,"toughness":null,"abilities":"Whenever a creature you control deals combat damage to a player, that player discards a card.","implemented":true,"requested":false,"tested":false,"bugged":false,"developer":null,"editions":[{"rarity":"Uncommon","gathererId":"19825","mtgoImageId":"19055","expansionCode":"MM","expansionName":"Mercadian Masques","cardNumber":"143"},{"rarity":"Rare","gathererId":"45332","mtgoImageId":"19055","expansionCode":"8ED","expansionName":"Eighth Edition","cardNumber":"139"}],"otherSide":null},{"id":7573,"name":"Mind Slash","cost":"1$B$B","type":"Enchantment","subType":null,"power":null,"toughness":null,"abilities":"{B}, Sacrifice a creature: Target opponent reveals his or her hand. You choose a card from it. That player discards that card. Activate this ability only any time you could cast a sorcery.","implemented":true,"requested":false,"tested":false,"bugged":false,"developer":null,"editions":[{"rarity":"Uncommon","gathererId":"21331","mtgoImageId":"21158","expansionCode":"NE","expansionName":"Nemesis","cardNumber":"59"},{"rarity":"Uncommon","gathererId":"45304","mtgoImageId":"21158","expansionCode":"8ED","expansionName":"Eighth Edition","cardNumber":"145"}],"otherSide":null},{"id":7574,"name":"Murderous Betrayal","cost":"B$B$B","type":"Enchantment","subType":null,"power":null,"toughness":null,"abilities":"{B}{B}, Pay half your life, rounded up: Destroy target nonblack creature. It can't be regenerated.","implemented":true,"requested":false,"tested":false,"bugged":false,"developer":null,"editions":[{"rarity":"Rare","gathererId":"21329","mtgoImageId":"21161","expansionCode":"NE","expansionName":"Nemesis","cardNumber":"61"},{"rarity":"Rare","gathererId":"45335","mtgoImageId":"21161","expansionCode":"8ED","expansionName":"Eighth Edition","cardNumber":"147"}],"otherSide":null},{"id":7575,"name":"Nausea","cost":"1$B","type":"Sorcery","subType":null,"power":null,"toughness":null,"abilities":"All creatures get -1/-1 until end of turn.","implemented":true,"requested":false,"tested":false,"bugged":false,"developer":null,"editions":[{"rarity":"Common","gathererId":"6088","mtgoImageId":"05606","expansionCode":"EX","expansionName":"Exodus","cardNumber":"67"},{"rarity":"Common","gathererId":"25623","mtgoImageId":"27720","expansionCode":"7E","expansionName":"Seventh Edition","cardNumber":"148"},{"rarity":"Common","gathererId":"45298","mtgoImageId":"27720","expansionCode":"8ED","expansionName":"Eighth Edition","cardNumber":"148"},{"rarity":"Common","gathererId":"413639","mtgoImageId":null,"expansionCode":"EMA","expansionName":"Eternal Masters","cardNumber":"97"}],"otherSide":null},{"id":7576,"name":"Phyrexian Plaguelord","cost":"3$B$B","type":"Creature","subType":"Carrier","power":"4","toughness":"4","abilities":"{tap}, Sacrifice Phyrexian Plaguelord: Target creature gets -4/-4 until end of turn.$Sacrifice a creature: Target creature gets -1/-1 until end of turn.","implemented":true,"requested":false,"tested":false,"bugged":false,"developer":null,"editions":[{"rarity":"Rare","gathererId":"12940","mtgoImageId":"09160","expansionCode":"GU","expansionName":"Urza's Legacy","cardNumber":"62"},{"rarity":"Rare","gathererId":"45327","mtgoImageId":"09160","expansionCode":"8ED","expansionName":"Eighth Edition","cardNumber":"153"},{"rarity":"Rare","gathererId":"209127","mtgoImageId":"09160","expansionCode":"DDE","expansionName":"Duel Decks: Phyrexia vs. the Coalition","cardNumber":"13"},{"rarity":"Rare","gathererId":"405338","mtgoImageId":null,"expansionCode":"C15","expansionName":"Commander 2015","cardNumber":"131"}],"otherSide":null},{"id":7577,"name":"Primeval Shambler","cost":"4$B","type":"Creature","subType":"Horror Mercenary","power":"3","toughness":"3","abilities":"{B}: Primeval Shambler gets +1/+1 until end of turn.","implemented":true,"requested":false,"tested":false,"bugged":false,"developer":null,"editions":[{"rarity":"Uncommon","gathererId":"19824","mtgoImageId":"19060","expansionCode":"MM","expansionName":"Mercadian Masques","cardNumber":"152"},{"rarity":"Uncommon","gathererId":"45312","mtgoImageId":"19060","expansionCode":"8ED","expansionName":"Eighth Edition","cardNumber":"156"}],"otherSide":null},{"id":7578,"name":"Sever Soul","cost":"3$B$B","type":"Sorcery","subType":null,"power":null,"toughness":null,"abilities":"Destroy target nonblack creature. It can't be regenerated. You gain life equal to its toughness.","implemented":true,"requested":false,"tested":false,"bugged":false,"developer":null,"editions":[{"rarity":"Common","gathererId":"19591","mtgoImageId":"19062","expansionCode":"MM","expansionName":"Mercadian Masques","cardNumber":"159"},{"rarity":"Uncommon","gathererId":"45317","mtgoImageId":"49239","expansionCode":"8ED","expansionName":"Eighth Edition","cardNumber":"162"}],"otherSide":null},{"id":7579,"name":"Diving Griffin","cost":"1$W$W","type":"Creature","subType":"Griffin","power":"2","toughness":"2","abilities":"Flying, vigilance","implemented":true,"requested":false,"tested":false,"bugged":false,"developer":null,"editions":[{"rarity":"Common","gathererId":"24548","mtgoImageId":"22049","expansionCode":"PR","expansionName":"Prophecy","cardNumber":"6"},{"rarity":"Common","gathererId":"45176","mtgoImageId":"22049","expansionCode":"8ED","expansionName":"Eighth Edition","cardNumber":"17"}],"otherSide":null},{"id":7580,"name":"Vampiric Spirit","cost":"2$B$B","type":"Creature","subType":"Spirit","power":"4","toughness":"3","abilities":"Flying$When Vampiric Spirit enters the battlefield, you lose 4 life.","implemented":true,"requested":false,"tested":false,"bugged":false,"developer":null,"editions":[{"rarity":"Rare","gathererId":"6575","mtgoImageId":"04729","expansionCode":"P2","expansionName":"Portal Second Age","cardNumber":"30"},{"rarity":"Rare","gathererId":"45328","mtgoImageId":"04729","expansionCode":"8ED","expansionName":"Eighth Edition","cardNumber":"170"}],"otherSide":null},{"id":7581,"name":"Vicious Hunger","cost":"B$B","type":"Sorcery","subType":null,"power":null,"toughness":null,"abilities":"Vicious Hunger deals 2 damage to target creature and you gain 2 life.","implemented":true,"requested":false,"tested":false,"bugged":false,"developer":null,"editions":[{"rarity":"Common","gathererId":"21317","mtgoImageId":"21209","expansionCode":"NE","expansionName":"Nemesis","cardNumber":"74"},{"rarity":"Common","gathererId":"45300","mtgoImageId":"21209","expansionCode":"8ED","expansionName":"Eighth Edition","cardNumber":"171"},{"rarity":"Common","gathererId":"202262","mtgoImageId":"21209","expansionCode":"DDD","expansionName":"Duel Decks: Garruk vs. Liliana","cardNumber":"50"}],"otherSide":null},{"id":7582,"name":"Bloodshot Cyclops","cost":"5$R","type":"Creature","subType":"Cyclops Giant","power":"4","toughness":"4","abilities":"{tap}, Sacrifice a creature: Bloodshot Cyclops deals damage equal to the sacrificed creature's power to target creature or player.","implemented":true,"requested":false,"tested":false,"bugged":false,"developer":null,"editions":[{"rarity":"Rare","gathererId":"15214","mtgoImageId":"15655","expansionCode":"CG","expansionName":"Urza's Destiny","cardNumber":"77"},{"rarity":"Rare","gathererId":"15792","mtgoImageId":"27552","expansionCode":"7E","expansionName":"Seventh Edition","cardNumber":"176"},{"rarity":"Rare","gathererId":"45387","mtgoImageId":"27552","expansionCode":"8ED","expansionName":"Eighth Edition","cardNumber":"179"}],"otherSide":null},{"id":7583,"name":"Cinder Wall","cost":"R","type":"Creature","subType":"Wall","power":"3","toughness":"3","abilities":"Defender <i>(This creature can't attack.)</i>$When Cinder Wall blocks, destroy it at end of combat.","implemented":true,"requested":false,"tested":false,"bugged":false,"developer":null,"editions":[{"rarity":"Common","gathererId":"4540","mtgoImageId":"02819","expansionCode":"WL","expansionName":"Weatherlight","cardNumber":"94"},{"rarity":"Common","gathererId":"45341","mtgoImageId":"49244","expansionCode":"8ED","expansionName":"Eighth Edition","cardNumber":"182"},{"rarity":"Common","gathererId":"243466","mtgoImageId":"49244","expansionCode":"DDG","expansionName":"Duel Decks: Knights vs. Dragons","cardNumber":"48"},{"rarity":"Common","gathererId":"382230","mtgoImageId":null,"expansionCode":"CNS","expansionName":"Magic: The Gathering-Conspiracy","cardNumber":"140"}],"otherSide":null},{"id":7584,"name":"Dwarven Demolition Team","cost":"2$R","type":"Creature","subType":"Dwarf","power":"1","toughness":"1","abilities":"{tap}: Destroy target Wall.","implemented":true,"requested":false,"tested":false,"bugged":false,"developer":null,"editions":[{"rarity":"Uncommon","gathererId":"190","mtgoImageId":"00071","expansionCode":"1E","expansionName":"Limited Edition Alpha","cardNumber":"143"},{"rarity":"Uncommon","gathererId":"485","mtgoImageId":"00071","expansionCode":"2E","expansionName":"Limited Edition Beta","cardNumber":"144"},{"rarity":"Uncommon","gathererId":"787","mtgoImageId":"00071","expansionCode":"2U","expansionName":"Unlimited Edition","cardNumber":"143"},{"rarity":"Uncommon","gathererId":"45367","mtgoImageId":"49245","expansionCode":"8ED","expansionName":"Eighth Edition","cardNumber":"184"}],"otherSide":null},{"id":7585,"name":"Goblin Glider","cost":"1$R","type":"Creature","subType":"Goblin","power":"1","toughness":"1","abilities":"Flying$Goblin Glider can't block.","implemented":true,"requested":false,"tested":false,"bugged":false,"developer":null,"editions":[{"rarity":"Common","gathererId":"6584","mtgoImageId":"04737","expansionCode":"P2","expansionName":"Portal Second Age","cardNumber":"98"},{"rarity":"Uncommon","gathererId":"20195","mtgoImageId":null,"expansionCode":"P3","expansionName":"Starter 1999","cardNumber":"102"},{"rarity":"Uncommon","gathererId":"25679","mtgoImageId":"27642","expansionCode":"7E","expansionName":"Seventh Edition","cardNumber":"189"},{"rarity":"Uncommon","gathererId":"45363","mtgoImageId":"27642","expansionCode":"8ED","expansionName":"Eighth Edition","cardNumber":"189"}],"otherSide":null},{"id":7586,"name":"Hammer of Bogardan","cost":"1$R$R","type":"Sorcery","subType":null,"power":null,"toughness":null,"abilities":"Hammer of Bogardan deals 3 damage to target creature or player.${2}{R}{R}{R}: Return Hammer of Bogardan from your graveyard to your hand. Activate this ability only during your upkeep.","implemented":true,"requested":false,"tested":false,"bugged":false,"developer":null,"editions":[{"rarity":"Rare","gathererId":"3452","mtgoImageId":"01917","expansionCode":"MI","expansionName":"Mirage","cardNumber":"181"},{"rarity":"Rare","gathererId":"15420","mtgoImageId":"01917","expansionCode":"6E","expansionName":"Sixth Edition","cardNumber":"188"},{"rarity":"Rare","gathererId":"49039","mtgoImageId":"01917","expansionCode":"8ED","expansionName":"Eighth Edition","cardNumber":"193"}],"otherSide":null},{"id":7587,"name":"Hulking Cyclops","cost":"3$R$R","type":"Creature","subType":"Cyclops","power":"5","toughness":"5","abilities":"Hulking Cyclops can't block.","implemented":true,"requested":false,"tested":false,"bugged":false,"developer":null,"editions":[{"rarity":"Uncommon","gathererId":"3691","mtgoImageId":"02189","expansionCode":"VI","expansionName":"Visions","cardNumber":"84"},{"rarity":"Uncommon","gathererId":"4345","mtgoImageId":"06700","expansionCode":"PO","expansionName":"Portal","cardNumber":"139"},{"rarity":"Uncommon","gathererId":"14644","mtgoImageId":"06700","expansionCode":"6E","expansionName":"Sixth Edition","cardNumber":"189"},{"rarity":"Uncommon","gathererId":"45371","mtgoImageId":"06700","expansionCode":"8ED","expansionName":"Eighth Edition","cardNumber":"195"}],"otherSide":null},{"id":7588,"name":"Inferno","cost":"5$R$R","type":"Instant","subType":null,"power":null,"toughness":null,"abilities":"Inferno deals 6 damage to each creature and each player.","implemented":true,"requested":false,"tested":false,"bugged":false,"developer":null,"editions":[{"rarity":"Rare","gathererId":"1797","mtgoImageId":"00787","expansionCode":"DK","expansionName":"The Dark","cardNumber":"70"},{"rarity":"Rare","gathererId":"2288","mtgoImageId":"00787","expansionCode":"4E","expansionName":"Fourth Edition","cardNumber":"223"},{"rarity":"Rare","gathererId":"4064","mtgoImageId":"02406","expansionCode":"5E","expansionName":"Fifth Edition","cardNumber":"243"},{"rarity":"Rare","gathererId":"11340","mtgoImageId":"02406","expansionCode":"6E","expansionName":"Sixth Edition","cardNumber":"191"},{"rarity":"Rare","gathererId":"15815","mtgoImageId":"27668","expansionCode":"7E","expansionName":"Seventh Edition","cardNumber":"198"},{"rarity":"Rare","gathererId":"45394","mtgoImageId":"27668","expansionCode":"8ED","expansionName":"Eighth Edition","cardNumber":"196"}],"otherSide":null},{"id":7589,"name":"Lava Hounds","cost":"2$R$R","type":"Creature","subType":"Hound","power":"4","toughness":"4","abilities":"Haste$When Lava Hounds enters the battlefield, it deals 4 damage to you.","implemented":true,"requested":false,"tested":false,"bugged":false,"developer":null,"editions":[{"rarity":"Uncommon","gathererId":"4555","mtgoImageId":"02936","expansionCode":"WL","expansionName":"Weatherlight","cardNumber":"109"},{"rarity":"Rare","gathererId":"45383","mtgoImageId":"02936","expansionCode":"8ED","expansionName":"Eighth Edition","cardNumber":"198"}],"otherSide":null},{"id":7590,"name":"Lesser Gargadon","cost":"2$R$R","type":"Creature","subType":"Beast","power":"6","toughness":"4","abilities":"Whenever Lesser Gargadon attacks or blocks, sacrifice a land.","implemented":true,"requested":false,"tested":false,"bugged":false,"developer":null,"editions":[{"rarity":"Uncommon","gathererId":"24647","mtgoImageId":"21952","expansionCode":"PR","expansionName":"Prophecy","cardNumber":"97"},{"rarity":"Uncommon","gathererId":"45370","mtgoImageId":"21952","expansionCode":"8ED","expansionName":"Eighth Edition","cardNumber":"199"}],"otherSide":null},{"id":7591,"name":"Orcish Spy","cost":"R","type":"Creature","subType":"Orc Rogue","power":"1","toughness":"1","abilities":"{tap}: Look at the top three cards of target player's library.","implemented":true,"requested":false,"tested":false,"bugged":false,"developer":null,"editions":[{"rarity":"Common","gathererId":"1961","mtgoImageId":"00979","expansionCode":"FE","expansionName":"Fallen Empires","cardNumber":"124"},{"rarity":"Common","gathererId":"45351","mtgoImageId":"49672","expansionCode":"8ED","expansionName":"Eighth Edition","cardNumber":"208"}],"otherSide":null},{"id":7592,"name":"Ridgeline Rager","cost":"2$R","type":"Creature","subType":"Beast","power":"1","toughness":"2","abilities":"{R}: Ridgeline Rager gets +1/+0 until end of turn.","implemented":true,"requested":false,"tested":false,"bugged":false,"developer":null,"editions":[{"rarity":"Common","gathererId":"24627","mtgoImageId":"22009","expansionCode":"PR","expansionName":"Prophecy","cardNumber":"100"},{"rarity":"Common","gathererId":"45346","mtgoImageId":"22009","expansionCode":"8ED","expansionName":"Eighth Edition","cardNumber":"215"}],"otherSide":null},{"id":7593,"name":"Sabretooth Tiger","cost":"2$R","type":"Creature","subType":"Cat","power":"2","toughness":"1","abilities":"First strike","implemented":true,"requested":false,"tested":false,"bugged":false,"developer":null,"editions":[{"rarity":"Common","gathererId":"2651","mtgoImageId":"01345","expansionCode":"IA","expansionName":"Ice Age","cardNumber":"215"},{"rarity":"Common","gathererId":"4085","mtgoImageId":"01345","expansionCode":"5E","expansionName":"Fifth Edition","cardNumber":"264"},{"rarity":"Common","gathererId":"11476","mtgoImageId":"01345","expansionCode":"6E","expansionName":"Sixth Edition","cardNumber":"203"},{"rarity":"Common","gathererId":"15807","mtgoImageId":"27770","expansionCode":"7E","expansionName":"Seventh Edition","cardNumber":"215"},{"rarity":"Common","gathererId":"45347","mtgoImageId":"27770","expansionCode":"8ED","expansionName":"Eighth Edition","cardNumber":"217"}],"otherSide":null},{"id":7594,"name":"Searing Wind","cost":"8$R","type":"Instant","subType":null,"power":null,"toughness":null,"abilities":"Searing Wind deals 10 damage to target creature or player.","implemented":true,"requested":false,"tested":false,"bugged":false,"developer":null,"editions":[{"rarity":"Rare","gathererId":"24650","mtgoImageId":"22056","expansionCode":"PR","expansionName":"Prophecy","cardNumber":"103"},{"rarity":"Rare","gathererId":"45397","mtgoImageId":"22056","expansionCode":"8ED","expansionName":"Eighth Edition","cardNumber":"218"}],"otherSide":null},{"id":7595,"name":"Shock Troops","cost":"3$R","type":"Creature","subType":"Human Soldier","power":"2","toughness":"2","abilities":"Sacrifice Shock Troops: Shock Troops deals 2 damage to target creature or player.","implemented":true,"requested":false,"tested":false,"bugged":false,"developer":null,"editions":[{"rarity":"Common","gathererId":"19609","mtgoImageId":"19184","expansionCode":"MM","expansionName":"Mercadian Masques","cardNumber":"212"},{"rarity":"Common","gathererId":"45350","mtgoImageId":"19184","expansionCode":"8ED","expansionName":"Eighth Edition","cardNumber":"223"}],"otherSide":null},{"id":7596,"name":"Sizzle","cost":"2$R","type":"Sorcery","subType":null,"power":null,"toughness":null,"abilities":"Sizzle deals 3 damage to each opponent.","implemented":true,"requested":false,"tested":false,"bugged":false,"developer":null,"editions":[{"rarity":"Common","gathererId":"19611","mtgoImageId":"19260","expansionCode":"MM","expansionName":"Mercadian Masques","cardNumber":"213"},{"rarity":"Common","gathererId":"45358","mtgoImageId":"49676","expansionCode":"8ED","expansionName":"Eighth Edition","cardNumber":"224"}],"otherSide":null},{"id":7597,"name":"Thieves' Auction","cost":"4$R$R$R","type":"Sorcery","subType":null,"power":null,"toughness":null,"abilities":"Exile all nontoken permanents. Starting with you, each player chooses one of the exiled cards and puts it onto the battlefield tapped under his or her control. Repeat this process until all cards exiled this way have been chosen.","implemented":true,"requested":true,"tested":false,"bugged":false,"developer":null,"editions":[{"rarity":"Rare","gathererId":"19722","mtgoImageId":"19202","expansionCode":"MM","expansionName":"Mercadian Masques","cardNumber":"218"},{"rarity":"Rare","gathererId":"45395","mtgoImageId":"19202","expansionCode":"8ED","expansionName":"Eighth Edition","cardNumber":"227"}],"otherSide":null},{"id":7598,"name":"Tremor","cost":"R","type":"Sorcery","subType":null,"power":null,"toughness":null,"abilities":"Tremor deals 1 damage to each creature without flying.","implemented":true,"requested":false,"tested":false,"bugged":false,"developer":null,"editions":[{"rarity":"Common","gathererId":"3706","mtgoImageId":"02278","expansionCode":"VI","expansionName":"Visions","cardNumber":"99"},{"rarity":"Common","gathererId":"6592","mtgoImageId":"05671","expansionCode":"P2","expansionName":"Portal Second Age","cardNumber":"118"},{"rarity":"Common","gathererId":"14613","mtgoImageId":"05671","expansionCode":"6E","expansionName":"Sixth Edition","cardNumber":"211"},{"rarity":"Common","gathererId":"20207","mtgoImageId":null,"expansionCode":"P3","expansionName":"Starter 1999","cardNumber":"121"},{"rarity":"Common","gathererId":"19614","mtgoImageId":"18982","expansionCode":"MM","expansionName":"Mercadian Masques","cardNumber":"220"},{"rarity":"Common","gathererId":"12988","mtgoImageId":"27842","expansionCode":"7E","expansionName":"Seventh Edition","cardNumber":"225"},{"rarity":"Common","gathererId":"45377","mtgoImageId":"05671","expansionCode":"8ED","expansionName":"Eighth Edition","cardNumber":"228"}],"otherSide":null},{"id":7599,"name":"Two-Headed Dragon","cost":"4$R$R","type":"Creature","subType":"Dragon","power":"4","toughness":"4","abilities":"Flying${1}{R}: Two-Headed Dragon gets +2/+0 until end of turn.$Two-Headed Dragon can't be blocked except by two or more creatures.$Two-Headed Dragon can block an additional creature.","implemented":true,"requested":false,"tested":false,"bugged":false,"developer":null,"editions":[{"rarity":"Rare","gathererId":"19711","mtgoImageId":"19321","expansionCode":"MM","expansionName":"Mercadian Masques","cardNumber":"221"},{"rarity":"Rare","gathererId":"45389","mtgoImageId":"19321","expansionCode":"8ED","expansionName":"Eighth Edition","cardNumber":"229"}],"otherSide":null},{"id":7600,"name":"Wall of Stone","cost":"1$R$R","type":"Creature","subType":"Wall","power":"0","toughness":"8","abilities":"Defender <i>(This creature can't attack.)</i>","implemented":true,"requested":false,"tested":false,"bugged":false,"developer":null,"editions":[{"rarity":"Uncommon","gathererId":"230","mtgoImageId":"00276","expansionCode":"1E","expansionName":"Limited Edition Alpha","cardNumber":"183"},{"rarity":"Uncommon","gathererId":"525","mtgoImageId":"00276","expansionCode":"2E","expansionName":"Limited Edition Beta","cardNumber":"184"},{"rarity":"Uncommon","gathererId":"827","mtgoImageId":"00276","expansionCode":"2U","expansionName":"Unlimited Edition","cardNumber":"183"},{"rarity":"Uncommon","gathererId":"1325","mtgoImageId":"00276","expansionCode":"3E","expansionName":"Revised Edition","cardNumber":"183"},{"rarity":"Uncommon","gathererId":"2314","mtgoImageId":"00276","expansionCode":"4E","expansionName":"Fourth Edition","cardNumber":"249"},{"rarity":"Uncommon","gathererId":"4095","mtgoImageId":"02507","expansionCode":"5E","expansionName":"Fifth Edition","cardNumber":"274"},{"rarity":"Uncommon","gathererId":"45368","mtgoImageId":"49246","expansionCode":"8ED","expansionName":"Eighth Edition","cardNumber":"232"}],"otherSide":null}],"totalRows":16976}